{
  "data": {
    "article": {},
    "attachments": {},
    "author_id": "1847712034361659392",
    "conversation_id": "2059595177858318608",
    "created_at": "2026-05-27T11:18:50.000Z",
    "edit_controls": {
      "editable_until": "2026-05-27T12:18:50.000Z",
      "edits_remaining": 5,
      "is_edit_eligible": true
    },
    "edit_history_tweet_ids": [
      "2059595177858318608"
    ],
    "entities": {},
    "geo": {},
    "id": "2059595177858318608",
    "lang": "ja",
    "note_tweet": {
      "entities": {}
    },
    "possibly_sensitive": false,
    "public_metrics": {
      "bookmark_count": 0,
      "impression_count": 0,
      "like_count": 0,
      "quote_count": 0,
      "reply_count": 0,
      "retweet_count": 0
    },
    "reply_settings": "mentionedUsers",
    "text": "感嘆する、三年でなんと70グラムも食べた"
  },
  "includes": {
    "tweets": [
      {
        "article": {},
        "attachments": {},
        "author_id": "1847712034361659392",
        "conversation_id": "2059595177858318608",
        "created_at": "2026-05-27T11:18:50.000Z",
        "edit_controls": {
          "editable_until": "2026-05-27T12:18:50.000Z",
          "edits_remaining": 5,
          "is_edit_eligible": true
        },
        "edit_history_tweet_ids": [
          "2059595177858318608"
        ],
        "entities": {},
        "geo": {},
        "id": "2059595177858318608",
        "lang": "ja",
        "note_tweet": {
          "entities": {}
        },
        "possibly_sensitive": false,
        "public_metrics": {
          "bookmark_count": 0,
          "impression_count": 0,
          "like_count": 0,
          "quote_count": 0,
          "reply_count": 0,
          "retweet_count": 0
        },
        "reply_settings": "mentionedUsers",
        "text": "感嘆する、三年でなんと70グラムも食べた"
      }
    ],
    "users": [
      {
        "created_at": "2024-10-19T18:51:20.000Z",
        "description": "官网：https://t.co/eW2O3fXtGc TG交流群：https://t.co/97NEazf5eZ DC交流群：https://t.co/a6mR5WgaIN 提问箱：https://t.co/fI760pi6Zw",
        "entities": {
          "description": {
            "urls": [
              {
                "display_url": "jile.bid",
                "end": 26,
                "expanded_url": "http://jile.bid",
                "start": 3,
                "url": "https://t.co/eW2O3fXtGc"
              },
              {
                "display_url": "t.me/yuanliaogeming",
                "end": 56,
                "expanded_url": "https://t.me/yuanliaogeming",
                "start": 33,
                "url": "https://t.co/97NEazf5eZ"
              },
              {
                "display_url": "discord.gg/XmNt8AXCEb",
                "end": 86,
                "expanded_url": "http://discord.gg/XmNt8AXCEb",
                "start": 63,
                "url": "https://t.co/a6mR5WgaIN"
              },
              {
                "display_url": "ngl.link/yumeng_0721",
                "end": 114,
                "expanded_url": "https://ngl.link/yumeng_0721",
                "start": 91,
                "url": "https://t.co/fI760pi6Zw"
              }
            ]
          }
        },
        "id": "1847712034361659392",
        "name": "极光实验室⚛️",
        "pinned_tweet_id": "2059552139131916649",
        "profile_image_url": "https://pbs.twimg.com/profile_images/2059551158373621760/mLGvZBuz_normal.jpg",
        "protected": false,
        "public_metrics": {
          "followers_count": 2103,
          "following_count": 932,
          "like_count": 24926,
          "listed_count": 2,
          "media_count": 384,
          "tweet_count": 3170
        },
        "username": "JiguangLab",
        "verified": false
      }
    ]
  }
}